rango_sdk/__init__.py
rango_sdk/config.py
rango_sdk/rango_client.py
rango_sdk/rango_response_entities.py
rango_sdk-0.7.1.dist-info/METADATA
rango_sdk-0.7.1.dist-info/WHEEL
rango_sdk-0.7.1.dist-info/top_level.txt
rango_sdk-0.7.1.dist-info/RECORD
